loraxmod/__init__.py
loraxmod/differ.py
loraxmod/extractor.py
loraxmod/parser.py
loraxmod/schema.py
loraxmod/schema_cache.py
tests/__init__.py
tests/conftest.py
tests/test_differ.py
tests/test_extractor.py
tests/test_schema.py
loraxmod-0.1.0.dist-info/METADATA
loraxmod-0.1.0.dist-info/WHEEL
loraxmod-0.1.0.dist-info/top_level.txt
loraxmod-0.1.0.dist-info/RECORD
