Metadata-Version: 2.4
Name: loraxmod
Version: 0.1.0
Summary: Schema-driven AST parsing and semantic diff for 170+ languages
Author: jackyHardDisk
License: MIT
Project-URL: Homepage, https://github.com/jackyHardDisk/loraxMod
Project-URL: Repository, https://github.com/jackyHardDisk/loraxMod
Project-URL: Documentation, https://github.com/jackyHardDisk/loraxMod/tree/master/loraxMod-py
Project-URL: Bug Tracker, https://github.com/jackyHardDisk/loraxMod/issues
Keywords: tree-sitter,ast,parser,semantic-diff,code-analysis
Classifier: Development Status :: 4 - Beta
Classifier: Intended Audience :: Developers
Classifier: License :: OSI Approved :: MIT License
Classifier: Programming Language :: Python :: 3
Classifier: Programming Language :: Python :: 3.10
Classifier: Programming Language :: Python :: 3.11
Classifier: Programming Language :: Python :: 3.12
Classifier: Topic :: Software Development :: Compilers
Classifier: Topic :: Software Development :: Code Generators
Requires-Python: >=3.10
Requires-Dist: tree-sitter>=0.25.0
Requires-Dist: tree-sitter-language-pack>=0.13.0
Provides-Extra: dev
Requires-Dist: pytest>=7.0; extra == "dev"
Requires-Dist: pytest-cov>=4.0; extra == "dev"
